ttool/__init__.py
ttool/read.py
toytool-0.0.2.dist-info/METADATA
toytool-0.0.2.dist-info/WHEEL
toytool-0.0.2.dist-info/top_level.txt
toytool-0.0.2.dist-info/RECORD
