Metadata-Version: 2.1
Name: toytool
Version: 0.0.2
Summary: toy-tool
Author: HandsomeBoy
Author-email: putaoisapig@163.com
Requires-Python: >=3.6
Requires-Dist: pillow
Requires-Dist: opencv-python
Requires-Dist: opencv-python-headless
